<?xml version="1.0" encoding="utf-8" ?><dwsync><file name="_base.php" server="woodlandtravelcenter.net//" local="3507394035" remote="3513676200" Dst="-1" /><file name="_functions.php" server="woodlandtravelcenter.net//" local="3507394035" remote="3513676200" Dst="-1" /><file name="checkbox.php" server="woodlandtravelcenter.net//" local="3507394035" remote="3513676200" Dst="-1" /><file name="color_picker.php" server="woodlandtravelcenter.net//" local="3507394035" remote="3513676200" Dst="-1" /><file name="dummy.php" server="woodlandtravelcenter.net//" local="3507394066" remote="3513676200" Dst="-1" /><file name="email.php" server="woodlandtravelcenter.net//" local="3507394066" remote="3513676200" Dst="-1" /><file name="file.php" server="woodlandtravelcenter.net//" local="3507394066" remote="3513676200" Dst="-1" /><file name="google-map.php" server="woodlandtravelcenter.net//" local="3507394066" remote="3513676200" Dst="-1" /><file name="image.php" server="woodlandtravelcenter.net//" local="3507394066" remote="3513676200" Dst="-1" /><file name="message.php" server="woodlandtravelcenter.net//" local="3507394067" remote="3513676200" Dst="-1" /><file name="number.php" server="woodlandtravelcenter.net//" local="3507394067" remote="3513676200" Dst="-1" /><file name="page_link.php" server="woodlandtravelcenter.net//" local="3507394067" remote="3513676200" Dst="-1" /><file name="password.php" server="woodlandtravelcenter.net//" local="3507394067" remote="3513676200" Dst="-1" /><file name="post_object.php" server="woodlandtravelcenter.net//" local="3507394067" remote="3513676200" Dst="-1" /><file name="radio.php" server="woodlandtravelcenter.net//" local="3507394067" remote="3513676200" Dst="-1" /><file name="relationship.php" server="woodlandtravelcenter.net//" local="3507394068" remote="3513676260" Dst="-1" /><file name="select.php" server="woodlandtravelcenter.net//" local="3507394068" remote="3513676260" Dst="-1" /><file name="tab.php" server="woodlandtravelcenter.net//" local="3507394068" remote="3513676260" Dst="-1" /><file name="taxonomy.php" server="woodlandtravelcenter.net//" local="3507394068" remote="3513676260" Dst="-1" /><file name="text.php" server="woodlandtravelcenter.net//" local="3507394068" remote="3513676260" Dst="-1" /><file name="textarea.php" server="woodlandtravelcenter.net//" local="3507394069" remote="3513676260" Dst="-1" /><file name="true_false.php" server="woodlandtravelcenter.net//" local="3507394069" remote="3513676260" Dst="-1" /><file name="user.php" server="woodlandtravelcenter.net//" local="3507394069" remote="3513676260" Dst="-1" /><file name="wysiwyg.php" server="woodlandtravelcenter.net//" local="3507394069" remote="3513676260" Dst="-1" /></dwsync>